README
setup.py
autodebug/__init__.py
autodebug.egg-info/PKG-INFO
autodebug.egg-info/SOURCES.txt
autodebug.egg-info/dependency_links.txt
autodebug.egg-info/top_level.txt