Metadata-Version: 1.1
Name: autodebug
Version: 1.0
Summary: Importing this module enables automatic post mortem debugging upon any exception. It uses module specified in envvar
Home-page: UNKNOWN
Author: Michał Podeszwa
Author-email: michal.podeszwa@gmail.com
License: BSD
Keywords: debugger debug automatic auto auto-debug
Platform: UNKNOWN
Classifier: Development Status :: 4 - Beta
Classifier: License :: OSI Approved :: BSD License
Classifier: Programming Language :: Python :: 2.7
Classifier: Programming Language :: Python :: 3.3
Classifier: Programming Language :: Python :: 3.4
Classifier: Topic :: Software Development :: Debuggers
